NASGrpcFileSystem/__init__.py
NASGrpcFileSystem/code_dict.py
NASGrpcFileSystem/grpc_copy_move_file.py
NASGrpcFileSystem/grpc_create_file.py
NASGrpcFileSystem/grpc_describe_file.py
NASGrpcFileSystem/grpc_file_handle.py
NASGrpcFileSystem/grpc_modify_file.py
NASGrpcFileSystem/grpc_options.py
NASGrpcFileSystem3/__init__.py
NASGrpcFileSystem3/code_dict.py
NASGrpcFileSystem3/grpc_copy_move_file.py
NASGrpcFileSystem3/grpc_create_file.py
NASGrpcFileSystem3/grpc_describe_file.py
NASGrpcFileSystem3/grpc_file_handle.py
NASGrpcFileSystem3/grpc_modify_file.py
NASGrpcFileSystem3/grpc_options.py
NASGrpcFileSystem3/proto/__init__.py
NASGrpcFileSystem3/proto/files_pb2.py
NASGrpcFileSystem3/proto/files_pb2_grpc.py
nas_grpc_filesytem/__init__.py
nas_grpc_filesytem/code_dict.py
nas_grpc_filesytem/grpc_copy_move_file.py
nas_grpc_filesytem/grpc_create_file.py
nas_grpc_filesytem/grpc_describe_file.py
nas_grpc_filesytem/grpc_file_handle.py
nas_grpc_filesytem/grpc_modify_file.py
nas_grpc_filesytem/grpc_options.py
nas_grpc_filesytem/proto/__init__.py
nas_grpc_filesytem/proto/files_pb2.py
nas_grpc_filesytem/proto/files_pb2_grpc.py
nas_grpc_filesytem-2.0.dist-info/METADATA
nas_grpc_filesytem-2.0.dist-info/WHEEL
nas_grpc_filesytem-2.0.dist-info/top_level.txt
nas_grpc_filesytem-2.0.dist-info/RECORD
