Metadata-Version: 2.1
Name: nas_grpc_filesytem
Version: 2.0
Summary: 一个使用gRPC客户端的Python文件处理器，用于处理ctec文件工作，
Author: Unnamed great master
Author-email: <gqylpy@outlook.com>
License: MIT
Classifier: Development Status :: 3 - Alpha
Classifier: Intended Audience :: Developers
Classifier: License :: OSI Approved :: MIT License
Classifier: Natural Language :: Chinese (Simplified)
Classifier: Natural Language :: English
Classifier: Operating System :: OS Independent
Classifier: Topic :: Software Development :: Libraries :: Python Modules
Classifier: Topic :: Artistic Software
Classifier: Topic :: Internet :: Log Analysis
Classifier: Topic :: Text Processing
Classifier: Programming Language :: Python :: 2.7
Classifier: Programming Language :: Python :: 3.5
Classifier: Programming Language :: Python :: 3.6
Classifier: Programming Language :: Python :: 3.7
Classifier: Programming Language :: Python :: 3.8
Classifier: Programming Language :: Python :: 3.9
Classifier: Programming Language :: Python :: 3.10
Classifier: Programming Language :: Python :: 3.11
Classifier: Programming Language :: Python :: 3.12
Classifier: Programming Language :: Python :: 3.13
Requires-Python: >=2.7
Requires-Dist: future ==0.18.2
Requires-Dist: grpcio >=1.62.3
Requires-Dist: werkzeug ==0.15.4
Requires-Dist: protobuf ==3.12.2
